{"caseSensitive":true,"concept":[{"code":"derivation","concept":[{"code":"revision","definition":"A derivation for which the resulting entity is a revised version of some original.","display":"Revision"},{"code":"quotation","definition":"The repeat of (some or all of) an entity, such as text or image, by someone who might or might not be its original author.","display":"Quotation"},{"code":"source","definition":"A primary source for a topic refers to something produced by some agent with direct experience and knowledge about the topic, at the time of the topic's study, without benefit from hindsight.","display":"Source"},{"code":"removal","definition":"A derivation for which the entity is removed from accessibility usually through the use of the Delete operation.","display":"Removal"}],"definition":"A transformation of an entity into another, an update of an entity resulting in a new one, or the construction of a new entity based on a pre-existing entity.","display":"Derivation"}],"contact":[{"telecom":[{"system":"url","value":"http://hl7.org/fhir"},{"system":"email","value":"fhir@lists.hl7.org"}]}],"content":"complete","date":"2021-01-17T07:06:13+11:00","description":"How an entity was used in an activity.","experimental":false,"extension":[{"url":"http://hl7.org/fhir/StructureDefinition/structuredefinition-wg","valueCode":"sec"},{"url":"http://hl7.org/fhir/StructureDefinition/structuredefinition-standards-status","valueCode":"trial-use"},{"url":"http://hl7.org/fhir/StructureDefinition/structuredefinition-fmm","valueInteger":3}],"id":"provenance-entity-role","identifier":[{"system":"urn:ietf:rfc:3986","value":"urn:oid:2.16.840.1.113883.4.642.4.437"}],"meta":{"lastUpdated":"2021-03-11T17:06:20.662+11:00","profile":["http://hl7.org/fhir/StructureDefinition/shareablecodesystem"]},"name":"ProvenanceEntityRole","publisher":"HL7 (FHIR Project)","resourceType":"CodeSystem","status":"draft","text":{"div":"<div xmlns=\"http://www.w3.org/1999/xhtml\">\n      \n      <h2>ProvenanceEntityRole</h2>\n      \n      <div>\n        \n        <p>How an entity was used in an activity.</p>\n\n      \n      </div>\n      \n      <p>This code system http://hl7.org/fhir/provenance-entity-role defines the following codes:</p>\n      \n      <table class=\"codes\">\n        \n        <tr>\n          \n          <td>\n            \n            <b>Lvl</b>\n          \n          </td>\n          \n          <td style=\"white-space:nowrap\">\n            \n            <b>Code</b>\n          \n          </td>\n          \n          <td>\n            \n            <b>Display</b>\n          \n          </td>\n          \n          <td>\n            \n            <b>Definition</b>\n          \n          </td>\n        \n        </tr>\n        \n        <tr>\n          \n          <td>1</td>\n          \n          <td style=\"white-space:nowrap\">derivation\n            \n            <a name=\"provenance-entity-role-derivation\"> </a>\n          \n          </td>\n          \n          <td>Derivation</td>\n          \n          <td>A transformation of an entity into another, an update of an entity resulting in a new one, or the construction of a new entity based on a pre-existing entity.</td>\n        \n        </tr>\n        \n        <tr>\n          \n          <td>2</td>\n          \n          <td style=\"white-space:nowrap\">  revision\n            \n            <a name=\"provenance-entity-role-revision\"> </a>\n          \n          </td>\n          \n          <td>Revision</td>\n          \n          <td>A derivation for which the resulting entity is a revised version of some original.</td>\n        \n        </tr>\n        \n        <tr>\n          \n          <td>2</td>\n          \n          <td style=\"white-space:nowrap\">  quotation\n            \n            <a name=\"provenance-entity-role-quotation\"> </a>\n          \n          </td>\n          \n          <td>Quotation</td>\n          \n          <td>The repeat of (some or all of) an entity, such as text or image, by someone who might or might not be its original author.</td>\n        \n        </tr>\n        \n        <tr>\n          \n          <td>2</td>\n          \n          <td style=\"white-space:nowrap\">  source\n            \n            <a name=\"provenance-entity-role-source\"> </a>\n          \n          </td>\n          \n          <td>Source</td>\n          \n          <td>A primary source for a topic refers to something produced by some agent with direct experience and knowledge about the topic, at the time of the topic's study, without benefit from hindsight.</td>\n        \n        </tr>\n        \n        <tr>\n          \n          <td>2</td>\n          \n          <td style=\"white-space:nowrap\">  removal\n            \n            <a name=\"provenance-entity-role-removal\"> </a>\n          \n          </td>\n          \n          <td>Removal</td>\n          \n          <td>A derivation for which the entity is removed from accessibility usually through the use of the Delete operation.</td>\n        \n        </tr>\n      \n      </table>\n    \n    </div>","status":"generated"},"title":"ProvenanceEntityRole","url":"http://hl7.org/fhir/provenance-entity-role","valueSet":"http://hl7.org/fhir/ValueSet/provenance-entity-role","version":"4.1.0"}