{
  "resourceType": "Observation",
  "id": "bgpanel",
  "text": {
    "status": "generated",
    "div": "<div xmlns=\"http://www.w3.org/1999/xhtml\"><p><b>Generated Narrative</b></p><p/><p><b>category</b>: <span>Laboratory</span></p><p><b>code</b>: <span>Blood Group Panel</span></p><p><b>subject</b>: <a>Patient/infant</a></p><p><b>effective</b>: 12 Mar. 2018, 3:07:54 am</p><p><b>hasMember</b>: </p><ul><li><a>Generated Summary: <span>Laboratory</span>; <span>Blood Group</span>; effective: 12 Mar. 2018, 3:07:54 am; <span>A</span></a></li><li><a>Generated Summary: <span>Laboratory</span>; <span>Blood Group</span>; effective: 12 Mar. 2018, 3:07:54 am; <span>A</span></a></li></ul></div>"
  },
  "status": "final",
  "category": [
    {
      "coding": [
        {
          "system": "http://terminology.hl7.org/CodeSystem/observation-category",
          "code": "laboratory",
          "display": "Laboratory"
        }
      ],
      "text": "Laboratory"
    }
  ],
  "code": {
    "coding": [
      {
        "system": "http://loinc.org",
        "code": "34532-2",
        "display": " Blood type and Indirect antibody screen panel - Blood"
      }
    ],
    "text": "Blood Group Panel"
  },
  "subject": {
    "reference": "Patient/infant"
  },
  "effectiveDateTime": "2018-03-11T16:07:54+00:00",
  "hasMember": [
    {
      "reference": "Observation/bloodgroup"
    },
    {
      "reference": "Observation/rhstatus"
    }
  ]
}