{"abstract":false,"baseDefinition":"http://hl7.org/fhir/StructureDefinition/PrimitiveType","contact":[{"telecom":[{"system":"url","value":"http://hl7.org/fhir"}]}],"date":"2021-03-11T17:06:20+11:00","derivation":"specialization","description":"Base StructureDefinition for base64Binary Type: A stream of bytes","differential":{"element":[{"comment":"A stream of bytes, base64 encoded","definition":"A stream of bytes","id":"base64Binary","max":"*","min":0,"path":"base64Binary","short":"Primitive Type base64Binary"},{"definition":"Primitive value for base64Binary","id":"base64Binary.value","max":"1","min":0,"path":"base64Binary.value","representation":["xmlAttr"],"short":"Primitive value for base64Binary","type":[{"code":"http://hl7.org/fhirpath/System.String","extension":[{"url":"http://hl7.org/fhir/StructureDefinition/structuredefinition-fhir-type","valueUri":"base64Binary"},{"url":"http://hl7.org/fhir/StructureDefinition/regex","valueString":"(\\s*([0-9a-zA-Z\\+/=]){4}\\s*)+"}]}]}]},"extension":[{"url":"http://hl7.org/fhir/StructureDefinition/structuredefinition-standards-status","valueCode":"normative"},{"url":"http://hl7.org/fhir/StructureDefinition/structuredefinition-normative-version","valueCode":"4.0.0"}],"fhirVersion":"4.1.0","id":"base64Binary","kind":"primitive-type","name":"base64Binary","publisher":"HL7 FHIR Standard","resourceType":"StructureDefinition","snapshot":{"element":[{"base":{"max":"*","min":0,"path":"base64Binary"},"comment":"A stream of bytes, base64 encoded","constraint":[{"expression":"hasValue() or (children().count() > id.count()) or $this is Parameters","human":"All FHIR elements must have a @value or children unless an empty Parameters resource","key":"ele-1","severity":"error","source":"http://hl7.org/fhir/StructureDefinition/Element","xpath":"@value|f:*|h:div|self::f:Parameters"}],"definition":"A stream of bytes","id":"base64Binary","isModifier":false,"isSummary":false,"max":"*","min":0,"path":"base64Binary","short":"Primitive Type base64Binary"},{"base":{"max":"1","min":0,"path":"Element.id"},"definition":"unique id for the element within a resource (for internal references)","id":"base64Binary.id","isModifier":false,"isSummary":false,"max":"1","min":0,"path":"base64Binary.id","representation":["xmlAttr"],"short":"xml:id (or equivalent in JSON)","type":[{"code":"http://hl7.org/fhirpath/System.String","extension":[{"url":"http://hl7.org/fhir/StructureDefinition/structuredefinition-fhir-type","valueUri":"string"}]}]},{"alias":["extensions","user content"],"base":{"max":"*","min":0,"path":"Element.extension"},"comment":"There can be no stigma associated with the use of extensions by any application, project, or standard - regardless of the institution or jurisdiction that uses or defines the extensions.  The use of extensions is what allows the FHIR specification to retain a core level of simplicity for everyone.","constraint":[{"expression":"hasValue() or (children().count() > id.count())","human":"All FHIR elements must have a @value or children","key":"ele-1","severity":"error","source":"http://hl7.org/fhir/StructureDefinition/Element","xpath":"@value|f:*|h:div"},{"expression":"extension.exists() != value.exists()","human":"Must have either extensions or value[x], not both","key":"ext-1","severity":"error","source":"http://hl7.org/fhir/StructureDefinition/Extension","xpath":"exists(f:extension)!=exists(f:*[starts-with(local-name(.), 'value')])"}],"definition":"May be used to represent additional information that is not part of the basic definition of the resource. To make the use of extensions safe and manageable, there is a strict set of governance  applied to the definition and use of extensions. Though any implementer can define an extension, there is a set of requirements that SHALL be met as part of the definition of the extension.","id":"base64Binary.extension","isModifier":false,"isSummary":false,"max":"*","min":0,"path":"base64Binary.extension","short":"Additional content defined by implementations","type":[{"code":"Extension"}]},{"base":{"max":"1","min":0,"path":"base64Binary.value"},"definition":"The actual value","id":"base64Binary.value","isModifier":false,"isSummary":false,"max":"1","min":0,"path":"base64Binary.value","representation":["xmlAttr"],"short":"Primitive value for base64Binary","type":[{"code":"http://hl7.org/fhirpath/System.String","extension":[{"url":"http://hl7.org/fhir/StructureDefinition/structuredefinition-fhir-type","valueUri":"base64Binary"},{"url":"http://hl7.org/fhir/StructureDefinition/regex","valueString":"(\\s*([0-9a-zA-Z\\+/=]){4}\\s*)+"}]}]}]},"status":"active","text":{"div":"<div xmlns=\"http://www.w3.org/1999/xhtml\">to do</div>","status":"generated"},"type":"base64Binary","url":"http://hl7.org/fhir/StructureDefinition/base64Binary","version":"4.1.0"}