{"abstract":false,"baseDefinition":"http://hl7.org/fhir/StructureDefinition/Extension","contact":[{"telecom":[{"system":"url","value":"http://hl7.org/special/committees/FHIR"}]}],"context":[{"expression":"Element","type":"element"}],"date":"2014-01-31","derivation":"constraint","description":"The work group that owns and maintains this resource.","differential":{"element":[{"comment":"This is mostly used in the main specification.","definition":"The work group that owns and maintains this resource.","id":"Extension","max":"1","min":0,"path":"Extension","short":"Owning Work Group"},{"id":"Extension.extension","max":"0","path":"Extension.extension"},{"fixedUri":"http://hl7.org/fhir/StructureDefinition/structuredefinition-wg","id":"Extension.url","path":"Extension.url"},{"binding":{"description":"An HL7 administrative unit that owns artifacts in the FHIR specification.","extension":[{"url":"http://hl7.org/fhir/build/StructureDefinition/definition","valueString":"An HL7 administrative unit that owns artifacts in the FHIR specification."},{"url":"http://hl7.org/fhir/StructureDefinition/elementdefinition-bindingName","valueString":"HL7Workgroup"}],"strength":"required","valueSet":"http://hl7.org/fhir/ValueSet/hl7-work-group"},"id":"Extension.value[x]","min":1,"path":"Extension.value[x]","type":[{"code":"code"}]}]},"extension":[{"url":"http://hl7.org/fhir/StructureDefinition/structuredefinition-wg","valueCode":"fhir"},{"url":"http://hl7.org/fhir/StructureDefinition/structuredefinition-fmm","valueInteger":1}],"fhirVersion":"4.1.0","id":"structuredefinition-wg","kind":"complex-type","mapping":[{"identity":"rim","name":"RIM Mapping","uri":"http://hl7.org/v3"}],"name":"wg","publisher":"Health Level Seven, Inc. - [WG Name] WG","resourceType":"StructureDefinition","snapshot":{"element":[{"base":{"max":"*","min":0,"path":"Extension"},"comment":"This is mostly used in the main specification.","condition":["ele-1"],"constraint":[{"expression":"hasValue() or (children().count() > id.count()) or $this is Parameters","human":"All FHIR elements must have a @value or children unless an empty Parameters resource","key":"ele-1","severity":"error","source":"http://hl7.org/fhir/StructureDefinition/Element","xpath":"@value|f:*|h:div|self::f:Parameters"},{"expression":"extension.exists() != value.exists()","human":"Must have either extensions or value[x], not both","key":"ext-1","severity":"error","source":"http://hl7.org/fhir/StructureDefinition/Extension","xpath":"exists(f:extension)!=exists(f:*[starts-with(local-name(.), 'value')])"}],"definition":"The work group that owns and maintains this resource.","id":"Extension","isModifier":false,"max":"1","min":0,"path":"Extension","short":"Owning Work Group"},{"base":{"max":"1","min":0,"path":"Element.id"},"definition":"Unique id for the element within a resource (for internal references). This may be any string value that does not contain spaces.","id":"Extension.id","isModifier":false,"isSummary":false,"mapping":[{"identity":"rim","map":"n/a"}],"max":"1","min":0,"path":"Extension.id","representation":["xmlAttr"],"short":"Unique id for inter-element referencing","type":[{"code":"http://hl7.org/fhirpath/System.String","extension":[{"url":"http://hl7.org/fhir/StructureDefinition/structuredefinition-fhir-type","valueUri":"string"}]}]},{"base":{"max":"*","min":0,"path":"Element.extension"},"constraint":[{"expression":"hasValue() or (children().count() > id.count())","human":"All FHIR elements must have a @value or children","key":"ele-1","severity":"error","source":"http://hl7.org/fhir/StructureDefinition/Element","xpath":"@value|f:*|h:div"},{"expression":"extension.exists() != value.exists()","human":"Must have either extensions or value[x], not both","key":"ext-1","severity":"error","source":"http://hl7.org/fhir/StructureDefinition/Extension","xpath":"exists(f:extension)!=exists(f:*[starts-with(local-name(.), \"value\")])"}],"definition":"An Extension","id":"Extension.extension","isModifier":false,"isSummary":false,"max":"0","min":0,"path":"Extension.extension","short":"Extension","slicing":{"description":"Extensions are always sliced by (at least) url","discriminator":[{"path":"url","type":"value"}],"rules":"open"},"type":[{"code":"Extension"}]},{"base":{"max":"1","min":1,"path":"Extension.url"},"comment":"The definition may point directly to a computable or human-readable definition of the extensibility codes, or it may be a logical URI as declared in some other specification. The definition SHALL be a URI for the Structure Definition defining the extension.","definition":"Source of the definition for the extension code - a logical name or a URL.","fixedUri":"http://hl7.org/fhir/StructureDefinition/structuredefinition-wg","id":"Extension.url","isModifier":false,"isSummary":false,"mapping":[{"identity":"rim","map":"N/A"}],"max":"1","min":1,"path":"Extension.url","representation":["xmlAttr"],"short":"identifies the meaning of the extension","type":[{"code":"http://hl7.org/fhirpath/System.String","extension":[{"url":"http://hl7.org/fhir/StructureDefinition/structuredefinition-fhir-type","valueUri":"uri"}]}]},{"base":{"max":"1","min":0,"path":"Extension.value[x]"},"binding":{"description":"An HL7 administrative unit that owns artifacts in the FHIR specification.","extension":[{"url":"http://hl7.org/fhir/build/StructureDefinition/definition","valueString":"An HL7 administrative unit that owns artifacts in the FHIR specification."},{"url":"http://hl7.org/fhir/StructureDefinition/elementdefinition-bindingName","valueString":"HL7Workgroup"}],"strength":"required","valueSet":"http://hl7.org/fhir/ValueSet/hl7-work-group"},"constraint":[{"expression":"hasValue() or (children().count() > id.count())","human":"All FHIR elements must have a @value or children","key":"ele-1","severity":"error","source":"http://hl7.org/fhir/StructureDefinition/Element","xpath":"@value|f:*|h:div"}],"definition":"Value of extension - must be one of a constrained set of the data types (see [Extensibility](extensibility.html) for a list).","id":"Extension.value[x]","isModifier":false,"isSummary":false,"mapping":[{"identity":"rim","map":"N/A"}],"max":"1","min":1,"path":"Extension.value[x]","short":"Value of extension","type":[{"code":"code"}]}]},"status":"draft","type":"Extension","url":"http://hl7.org/fhir/StructureDefinition/structuredefinition-wg","version":"4.1.0"}