{"resourceType":"ValueSet","id":"enteral-route","meta":{"lastUpdated":"2017-04-19T07:44:43.294+10:00","profile":["http://hl7.org/fhir/StructureDefinition/shareablevalueset"]},"extension":[{"url":"http://hl7.org/fhir/StructureDefinition/structuredefinition-ballot-status","valueString":"Informative"},{"url":"http://hl7.org/fhir/StructureDefinition/structuredefinition-fmm","valueInteger":2},{"url":"http://hl7.org/fhir/StructureDefinition/structuredefinition-wg","valueCode":"oo"}],"url":"http://hl7.org/fhir/ValueSet/enteral-route","identifier":[{"system":"urn:ietf:rfc:3986","value":"urn:oid:2.16.840.1.113883.4.642.3.381"}],"version":"3.0.2","name":"Enteral Route Codes","status":"draft","experimental":true,"date":"2017-04-19T07:44:43+10:00","publisher":"FHIR NutritionOrder team","contact":[{"telecom":[{"system":"url","value":"http://hl7.org/fhir"}]}],"description":"EnteralRouteOfAdministration: Codes specifying the route of administration of enteral formula.  This value set is composed of HL7 v3 codes and is provided as a suggestive example.","compose":{"include":[{"system":"http://hl7.org/fhir/v3/RouteOfAdministration","concept":[{"code":"PO"},{"code":"EFT"},{"code":"ENTINSTL"},{"code":"GT"},{"code":"NGT"},{"code":"OGT"},{"code":"GJT"},{"code":"JJTINSTL"},{"code":"OJJ"}]}]},"expansion":{"identifier":"urn:uuid:e1bed13f-f6d7-4653-a103-287a6626455d","timestamp":"2017-03-16T20:55:04+11:00","total":9,"parameter":[{"name":"version","valueUri":"http://hl7.org/fhir/v3/RouteOfAdministration|2016-11-11"}],"contains":[{"system":"http://hl7.org/fhir/v3/RouteOfAdministration","code":"PO","display":"Swallow, oral"},{"system":"http://hl7.org/fhir/v3/RouteOfAdministration","code":"EFT","display":"Instillation, enteral feeding tube"},{"system":"http://hl7.org/fhir/v3/RouteOfAdministration","code":"ENTINSTL","display":"Instillation, enteral"},{"system":"http://hl7.org/fhir/v3/RouteOfAdministration","code":"GT","display":"Instillation, gastrostomy tube"},{"system":"http://hl7.org/fhir/v3/RouteOfAdministration","code":"NGT","display":"Instillation, nasogastric tube"},{"system":"http://hl7.org/fhir/v3/RouteOfAdministration","code":"OGT","display":"Instillation, orogastric tube"},{"system":"http://hl7.org/fhir/v3/RouteOfAdministration","code":"GJT","display":"Instillation, gastro-jejunostomy tube"},{"system":"http://hl7.org/fhir/v3/RouteOfAdministration","code":"JJTINSTL","display":"Instillation, jejunostomy tube"},{"system":"http://hl7.org/fhir/v3/RouteOfAdministration","code":"OJJ","display":"Instillation, orojejunum tube"}]}}