{"resourceType":"SearchParameter","id":"Communication-received","extension":[{"url":"http://hl7.org/fhir/StructureDefinition/structuredefinition-standards-status","valueCode":"normative"}],"url":"http://hl7.org/fhir/SearchParameter/Communication-received","version":"4.5.0","name":"received","status":"active","experimental":false,"date":"2020-08-20T17:41:31+10:00","publisher":"Health Level Seven International (Patient Care)","contact":[{"telecom":[{"system":"url","value":"http://hl7.org/fhir"}]},{"telecom":[{"system":"url","value":"http://www.hl7.org/Special/committees/patientcare/index.cfm"}]}],"description":"When received","code":"received","base":["Communication"],"type":"date","expression":"Communication.received","xpath":"f:Communication/f:received","xpathUsage":"normal","comparator":["eq","ne","gt","ge","lt","le","sa","eb","ap"]}