{"resourceType":"ConceptMap","id":"v2-address-use","url":"http://hl7.org/fhir/ConceptMap/v2-address-use","name":"v2 map for AddressUse","status":"draft","publisher":"HL7 (FHIR Project)","contact":[{"telecom":[{"system":"other","value":"http://hl7.org/fhir"},{"system":"email","value":"fhir@lists.hl7.org"}]}],"date":"2015-10-24T07:41:03+11:00","description":"v2 Map (0190)","sourceReference":{"reference":"http://hl7.org/fhir/ValueSet/address-use"},"targetReference":{"reference":"http://hl7.org/fhir/ValueSet/v2-0190"},"element":[{"codeSystem":"http://hl7.org/fhir/address-use","code":"home","target":[{"codeSystem":"http://hl7.org/fhir/v2/0190","code":"H","equivalence":"equivalent"}]},{"codeSystem":"http://hl7.org/fhir/address-use","code":"work","target":[{"codeSystem":"http://hl7.org/fhir/v2/0190","code":"O","equivalence":"equivalent"}]},{"codeSystem":"http://hl7.org/fhir/address-use","code":"temp","target":[{"codeSystem":"http://hl7.org/fhir/v2/0190","code":"C","equivalence":"equivalent"}]},{"codeSystem":"http://hl7.org/fhir/address-use","code":"old","target":[{"codeSystem":"http://hl7.org/fhir/v2/0190","code":"BA","equivalence":"wider","comments":"unclear about old addresses"}]}]}