{"resourceType":"Conformance","id":"base2","meta":{"lastUpdated":"2015-10-24T07:41:03.495+11:00"},"url":"http://hl7.org/fhir/Conformance/base2","version":"1.0.2-7202","name":"Base FHIR Conformance Statement (Empty)","status":"draft","experimental":true,"publisher":"FHIR Project Team","contact":[{"telecom":[{"system":"other","value":"http://hl7.org/fhir"}]}],"date":"2015-10-24T07:41:03+11:00","description":"This is the base conformance statement for FHIR. It represents a server that provides the none of the functionality defined by FHIR. It is provided to use as a template for system designers to build their own conformance statements from. A conformance profile has to contain something, so this contains a read of a Conformance Statement","kind":"capability","software":{"name":"Insert your softwware name here..."},"fhirVersion":"1.0.2","acceptUnknown":"no","format":["xml","json"],"rest":[{"mode":"server","documentation":"An empty conformance statement","security":{"cors":true,"service":[{"coding":[{"system":"http://hl7.org/fhir/restful-security-service","code":"SMART-on-FHIR","display":"SMART-on-FHIR"}],"text":"See http://docs.smarthealthit.org/"}],"description":"This is the conformance statement to declare that the server supports SMART-on-FHIR. See the SMART-on-FHIR docs for the extension that would go with such a server"},"resource":[{"type":"Conformance","interaction":[{"code":"read","documentation":"Read Conformance Resource"}]}]}]}