{"resourceType":"ValueSet","id":"v3-SpecimenType","meta":{"lastUpdated":"2015-07-31T00:00:00.000+10:00","profile":["http://hl7.org/fhir/StructureDefinition/valueset-shareable-definition"]},"url":"http://hl7.org/fhir/ValueSet/v3-SpecimenType","version":"2015-07-31","name":"v3 Code System SpecimenType","status":"active","experimental":false,"publisher":"HL7, Inc","contact":[{"telecom":[{"system":"other","value":"http://hl7.org"}]}],"date":"2015-07-31","description":"**** MISSING DEFINITIONS ****","codeSystem":{"extension":[{"url":"http://hl7.org/fhir/StructureDefinition/valueset-oid","valueUri":"urn:oid:2.16.840.1.113883.5.129"}],"system":"http://hl7.org/fhir/v3/SpecimenType","caseSensitive":true,"concept":[{"code":"_SpecimenEntityType","abstract":true,"display":"SpecimenEntityType","definition":"SpecimenEntityType","concept":[{"code":"ABS","abstract":false,"display":"Abcess","definition":"Abcess"},{"code":"AMN","abstract":false,"display":"Amniotic fluid","definition":"Amniotic fluid"},{"code":"ASP","abstract":false,"display":"Aspirate","definition":"Aspirate"},{"code":"BBL","abstract":false,"display":"Blood bag","definition":"Blood bag"},{"code":"BDY","abstract":false,"display":"Whole body","definition":"Whole body"},{"code":"BIFL","abstract":false,"display":"Bile fluid","definition":"Bile fluid"},{"code":"BLD","abstract":false,"display":"Whole blood","definition":"Whole blood"},{"code":"BLDA","abstract":false,"display":"Blood arterial","definition":"Blood arterial"},{"code":"BLDC","abstract":false,"display":"Blood capillary","definition":"Blood capillary"},{"code":"BLDCO","abstract":false,"display":"Blood - cord","definition":"Blood - cord"},{"code":"BLDV","abstract":false,"display":"Blood venous","definition":"Blood venous"},{"code":"BON","abstract":false,"display":"Bone","definition":"Bone"},{"code":"BPH","abstract":false,"display":"Basophils","definition":"Basophils"},{"code":"BPU","abstract":false,"display":"Blood product unit","definition":"Blood product unit"},{"code":"BRN","abstract":false,"display":"Burn","definition":"Burn"},{"code":"BRO","abstract":false,"display":"Bronchial","definition":"Bronchial"},{"code":"BRTH","abstract":false,"display":"Exhaled gas (\u003dbreath)","definition":"Exhaled gas (\u003dbreath)"},{"code":"CALC","abstract":false,"display":"Calculus (\u003dStone)","definition":"Calculus (\u003dStone)"},{"code":"CDM","abstract":false,"display":"Cardiac muscle","definition":"Cardiac muscle"},{"code":"CNJT","abstract":false,"display":"Conjunctiva","definition":"Conjunctiva"},{"code":"CNL","abstract":false,"display":"Cannula","definition":"Cannula"},{"code":"COL","abstract":false,"display":"Colostrum","definition":"Colostrum"},{"code":"CRN","abstract":false,"display":"Cornea","definition":"Cornea"},{"code":"CSF","abstract":false,"display":"Cerebral spinal fluid","definition":"Cerebral spinal fluid"},{"code":"CTP","abstract":false,"display":"Catheter tip","definition":"Catheter tip"},{"code":"CUR","abstract":false,"display":"Curettage","definition":"Curettage"},{"code":"CVM","abstract":false,"display":"Cervical mucus","definition":"Cervical mucus"},{"code":"CVX","abstract":false,"display":"Cervix","definition":"Cervix"},{"code":"CYST","abstract":false,"display":"Cyst","definition":"Cyst"},{"code":"DIAF","abstract":false,"display":"Dialysis fluid","definition":"Dialysis fluid"},{"code":"DOSE","abstract":false,"display":"Dose med or substance","definition":"Dose med or substance"},{"code":"DRN","abstract":false,"display":"Drain","definition":"Drain"},{"code":"DUFL","abstract":false,"display":"Duodenal fluid","definition":"Duodenal fluid"},{"code":"EAR","abstract":false,"display":"Ear","definition":"Ear"},{"code":"EARW","abstract":false,"display":"Ear wax (cerumen)","definition":"Ear wax (cerumen)"},{"code":"ELT","abstract":false,"display":"Electrode","definition":"Electrode"},{"code":"ENDC","abstract":false,"display":"Endocardium","definition":"Endocardium"},{"code":"ENDM","abstract":false,"display":"Endometrium","definition":"Endometrium"},{"code":"EOS","abstract":false,"display":"Eosinophils","definition":"Eosinophils"},{"code":"EYE","abstract":false,"display":"Eye","definition":"Eye"},{"code":"FIB","abstract":false,"display":"Fibroblasts","definition":"Fibroblasts"},{"code":"FIST","abstract":false,"display":"Fistula","definition":"Fistula"},{"code":"FLT","abstract":false,"display":"Filter","definition":"Filter"},{"code":"FLU","abstract":false,"display":"Body fluid, unsp","definition":"Body fluid, unsp"},{"code":"FOOD","abstract":false,"display":"Food sample","definition":"Food sample"},{"code":"GAS","abstract":false,"display":"Gas","definition":"Gas"},{"code":"GAST","abstract":false,"display":"Gastric fluid/contents","definition":"Gastric fluid/contents"},{"code":"GEN","abstract":false,"display":"Genital","definition":"Genital"},{"code":"GENC","abstract":false,"display":"Genital cervix","definition":"Genital cervix"},{"code":"GENF","abstract":false,"display":"Genital fluid","definition":"Genital fluid"},{"code":"GENL","abstract":false,"display":"Genital lochia","definition":"Genital lochia"},{"code":"GENV","abstract":false,"display":"Genital vaginal","definition":"Genital vaginal"},{"code":"HAR","abstract":false,"display":"Hair","definition":"Hair"},{"code":"IHG","abstract":false,"display":"Inhaled Gas","definition":"Inhaled Gas"},{"code":"ISLT","abstract":false,"display":"Isolate","definition":"Isolate"},{"code":"IT","abstract":false,"display":"Intubation tube","definition":"Intubation tube"},{"code":"LAM","abstract":false,"display":"Lamella","definition":"Lamella"},{"code":"LIQ","abstract":false,"display":"Liquid NOS","definition":"Liquid NOS"},{"code":"LN","abstract":false,"display":"Line","definition":"Line"},{"code":"LNA","abstract":false,"display":"Line arterial","definition":"Line arterial"},{"code":"LNV","abstract":false,"display":"Line venous","definition":"Line venous"},{"code":"LYM","abstract":false,"display":"Lymphocytes","definition":"Lymphocytes"},{"code":"MAC","abstract":false,"display":"Macrophages","definition":"Macrophages"},{"code":"MAR","abstract":false,"display":"Marrow (bone)","definition":"Marrow (bone)"},{"code":"MBLD","abstract":false,"display":"Menstrual blood","definition":"Menstrual blood"},{"code":"MEC","abstract":false,"display":"Meconium","definition":"Meconium"},{"code":"MILK","abstract":false,"display":"Breast milk","definition":"Breast milk"},{"code":"MLK","abstract":false,"display":"Milk","definition":"Milk"},{"code":"NAIL","abstract":false,"display":"Nail","definition":"Nail"},{"code":"NOS","abstract":false,"display":"Nose (nasal passage)","definition":"Nose (nasal passage)"},{"code":"PAFL","abstract":false,"display":"Pancreatic fluid","definition":"Pancreatic fluid"},{"code":"PAT","abstract":false,"display":"Patient","definition":"Patient"},{"code":"PLAS","abstract":false,"display":"Plasma","definition":"Plasma"},{"code":"PLB","abstract":false,"display":"Plasma bag","definition":"Plasma bag"},{"code":"PLC","abstract":false,"display":"Placenta","definition":"Placenta"},{"code":"PLR","abstract":false,"display":"Pleural fluid (thoracentesis fld)","definition":"Pleural fluid (thoracentesis fld)"},{"code":"PMN","abstract":false,"display":"Polymorphonuclear neutrophils","definition":"Polymorphonuclear neutrophils"},{"code":"PPP","abstract":false,"display":"Platelet poor plasma","definition":"Platelet poor plasma"},{"code":"PRP","abstract":false,"display":"Platelet rich plasma","definition":"Platelet rich plasma"},{"code":"PRT","abstract":false,"display":"Peritoneal fluid /ascites","definition":"Peritoneal fluid /ascites"},{"code":"PUS","abstract":false,"display":"Pus","definition":"Pus"},{"code":"RBC","abstract":false,"display":"Erythrocytes","definition":"Erythrocytes"},{"code":"SAL","abstract":false,"display":"Saliva","definition":"Saliva"},{"code":"SER","abstract":false,"display":"Serum","definition":"Serum"},{"code":"SKM","abstract":false,"display":"Skeletal muscle","definition":"Skeletal muscle"},{"code":"SKN","abstract":false,"display":"Skin","definition":"Skin"},{"code":"SMN","abstract":false,"display":"Seminal fluid","definition":"Seminal fluid"},{"code":"SMPLS","abstract":false,"display":"Seminal plasma","definition":"Seminal plasma"},{"code":"SNV","abstract":false,"display":"Synovial fluid (Joint fluid)","definition":"Synovial fluid (Joint fluid)"},{"code":"SPRM","abstract":false,"display":"Spermatozoa","definition":"Spermatozoa"},{"code":"SPT","abstract":false,"display":"Sputum","definition":"Sputum"},{"code":"SPTC","abstract":false,"display":"Sputum - coughed","definition":"Sputum - coughed"},{"code":"SPTT","abstract":false,"display":"Sputum - tracheal aspirate","definition":"Sputum - tracheal aspirate"},{"code":"STL","abstract":false,"display":"Stool \u003d Fecal","definition":"Stool \u003d Fecal"},{"code":"SWT","abstract":false,"display":"Sweat","definition":"Sweat"},{"code":"TEAR","abstract":false,"display":"Tears","definition":"Tears"},{"code":"THRB","abstract":false,"display":"Thrombocyte (platelet)","definition":"Thrombocyte (platelet)"},{"code":"THRT","abstract":false,"display":"Throat","definition":"Throat"},{"code":"TISG","abstract":false,"display":"Tissue gall bladder","definition":"Tissue gall bladder"},{"code":"TISPL","abstract":false,"display":"Tissue placenta","definition":"Tissue placenta"},{"code":"TISS","abstract":false,"display":"Tissue, unspecified","definition":"Tissue, unspecified"},{"code":"TISU","abstract":false,"display":"Tissue ulcer","definition":"Tissue ulcer"},{"code":"TLGI","abstract":false,"display":"Tissue large intestine","definition":"Tissue large intestine"},{"code":"TLNG","abstract":false,"display":"Tissue lung","definition":"Tissue lung"},{"code":"TSMI","abstract":false,"display":"Tissue small intestine Tissue ulcer","definition":"Tissue small intestine Tissue ulcer"},{"code":"TUB","abstract":false,"display":"Tube, unspecified","definition":"Tube, unspecified"},{"code":"ULC","abstract":false,"display":"Ulcer","definition":"Ulcer"},{"code":"UMB","abstract":false,"display":"Umbilical blood","definition":"Umbilical blood"},{"code":"UMED","abstract":false,"display":"Unknown medicine","definition":"Unknown medicine"},{"code":"UR","abstract":false,"display":"Urine","definition":"Urine"},{"code":"URC","abstract":false,"display":"Urine clean catch","definition":"Urine clean catch"},{"code":"URNS","abstract":false,"display":"Urine sediment","definition":"Urine sediment"},{"code":"URT","abstract":false,"display":"Urine catheter","definition":"Urine catheter"},{"code":"URTH","abstract":false,"display":"Urethra","definition":"Urethra"},{"code":"USUB","abstract":false,"display":"Unknown substance","definition":"Unknown substance"},{"code":"VOM","abstract":false,"display":"Vomitus","definition":"Vomitus"},{"code":"WAT","abstract":false,"display":"Water","definition":"Water"},{"code":"WBC","abstract":false,"display":"Leukocytes","definition":"Leukocytes"},{"code":"WICK","abstract":false,"display":"Wick","definition":"Wick"},{"code":"WND","abstract":false,"display":"Wound","definition":"Wound"},{"code":"WNDA","abstract":false,"display":"Wound abscess","definition":"Wound abscess"},{"code":"WNDD","abstract":false,"display":"Wound drainage","definition":"Wound drainage"},{"code":"WNDE","abstract":false,"display":"Wound exudate","definition":"Wound exudate"}]}]}}